geoarrow/c/__init__.py
geoarrow/c/_lib.cpython-313-x86_64-linux-musl.so
geoarrow/c/_lib.pyx
geoarrow/c/_version.py
geoarrow/c/lib.py
geoarrow/c/geoarrow/array_reader.c
geoarrow/c/geoarrow/array_view.c
geoarrow/c/geoarrow/array_writer.c
geoarrow/c/geoarrow/builder.c
geoarrow/c/geoarrow/double_parse_fast_float.cc
geoarrow/c/geoarrow/double_parse_std.c
geoarrow/c/geoarrow/double_print.c
geoarrow/c/geoarrow/fast_float.h
geoarrow/c/geoarrow/geoarrow.h
geoarrow/c/geoarrow/geoarrow.hpp
geoarrow/c/geoarrow/geoarrow_config.h
geoarrow/c/geoarrow/geoarrow_type.h
geoarrow/c/geoarrow/geoarrow_type_inline.h
geoarrow/c/geoarrow/geometry.c
geoarrow/c/geoarrow/kernel.c
geoarrow/c/geoarrow/metadata.c
geoarrow/c/geoarrow/native_writer.c
geoarrow/c/geoarrow/schema.c
geoarrow/c/geoarrow/schema_view.c
geoarrow/c/geoarrow/util.c
geoarrow/c/geoarrow/visitor.c
geoarrow/c/geoarrow/wkb_reader.c
geoarrow/c/geoarrow/wkb_writer.c
geoarrow/c/geoarrow/wkt_reader.c
geoarrow/c/geoarrow/wkt_writer.c
geoarrow/c/geoarrow/hpp/array_reader.hpp
geoarrow/c/geoarrow/hpp/array_util.hpp
geoarrow/c/geoarrow/hpp/array_writer.hpp
geoarrow/c/geoarrow/hpp/arrow_extension_type.hpp
geoarrow/c/geoarrow/hpp/exception.hpp
geoarrow/c/geoarrow/hpp/geometry_data_type.hpp
geoarrow/c/geoarrow/hpp/geometry_type_traits.hpp
geoarrow/c/geoarrow/hpp/internal.hpp
geoarrow/c/geoarrow/hpp/wkb_util.hpp
geoarrow/c/geoarrow/nanoarrow/nanoarrow.c
geoarrow/c/geoarrow/nanoarrow/nanoarrow.h
geoarrow/c/geoarrow/nanoarrow/nanoarrow.hpp
geoarrow/c/geoarrow/ryu/common.h
geoarrow/c/geoarrow/ryu/d2fixed_full_table.h
geoarrow/c/geoarrow/ryu/d2s.c
geoarrow/c/geoarrow/ryu/d2s_full_table.h
geoarrow/c/geoarrow/ryu/d2s_intrinsics.h
geoarrow/c/geoarrow/ryu/digit_table.h
geoarrow/c/geoarrow/ryu/ryu.h
geoarrow/c/geoarrow_python/geoarrow_config.h
geoarrow/c/geoarrow_python/geoarrow_python.h
geoarrow_c.libs/libgcc_s-0cd532bd.so.1
geoarrow_c.libs/libstdc++-5d72f927.so.6.0.33
geoarrow_c-0.3.1.dist-info/METADATA
geoarrow_c-0.3.1.dist-info/WHEEL
geoarrow_c-0.3.1.dist-info/top_level.txt
geoarrow_c-0.3.1.dist-info/RECORD
