Metadata-Version: 2.1
Name: geoarrow-c
Version: 0.3.1
Summary: Python bindings to the geoarrow C and C++ implementation
Author-email: Dewey Dunnington <dewey@dunnington.ca>
License: Apache-2.0
Project-URL: homepage, https://geoarrow.org
Project-URL: repository, https://github.com/geoarrow/geoarrow-c
Requires-Python: >=3.8
Provides-Extra: test
Requires-Dist: pyarrow ; extra == 'test'
Requires-Dist: pytest ; extra == 'test'
Requires-Dist: numpy ; extra == 'test'
